GMDN/__init__.py
GMDN/helpers.py
GMDN-1.0.1.dist-info/LICENSE
GMDN-1.0.1.dist-info/METADATA
GMDN-1.0.1.dist-info/WHEEL
GMDN-1.0.1.dist-info/top_level.txt
GMDN-1.0.1.dist-info/RECORD
