Metadata-Version: 2.1
Name: GMDN
Version: 1.0.1
Summary: A python implementation of XKCD''s Geothmetic Meandian ( https://xkcd.com/2435/ )
Home-page: https://github.com/BollaBerg/GMDN
Author: Andreas B. Berg
Author-email: berg.andreasb+PyPi@gmail.com
License: UNKNOWN
Project-URL: Bug Tracker, https://github.com/BollaBerg/GMDN/issues
Keywords: XKCD,GMDN,Geothmetic meandian,Math
Platform: UNKNOWN
Classifier: Programming Language :: Python :: 3.8
Classifier: Programming Language :: Python :: 3.9
Classifier: License :: OSI Approved :: MIT License
Classifier: Operating System :: OS Independent
Classifier: Development Status :: 5 - Production/Stable
Requires-Python: >=3.8
